p2p/__init__.py
p2p/adapters.py
p2p/auth.py
p2p/cache.py
p2p/decorators.py
p2p/errors.py
p2p/filters.py
p2p/models.py
p2p/tests.py
p2p/utils.py
p2p_latimes-2.0.36.dist-info/DESCRIPTION.rst
p2p_latimes-2.0.36.dist-info/LICENSE.txt
p2p_latimes-2.0.36.dist-info/METADATA
p2p_latimes-2.0.36.dist-info/RECORD
p2p_latimes-2.0.36.dist-info/WHEEL
p2p_latimes-2.0.36.dist-info/metadata.json
p2p_latimes-2.0.36.dist-info/top_level.txt
