Metadata-Version: 2.0
Name: p2p-latimes
Version: 2.0.36
Summary: Tribune P2P API wrapper
Home-page: http://github.com/datadesk/p2p-python
Author: Tribune News Applications, Los Angeles Times Data Desk
Author-email: datadesk@latimes.com
License: MIT
Platform: UNKNOWN
Requires-Dist: python-dateutil
Requires-Dist: requests
Requires-Dist: iso8601
Requires-Dist: pytz
